MANIFEST.in
README.rst
setup.py
src/AUTHORS.txt
src/HISTORY.txt
src/README.txt
src/sphinxjp/__init__.py
src/sphinxjp.themes.tinkeralizarin.egg-info/PKG-INFO
src/sphinxjp.themes.tinkeralizarin.egg-info/SOURCES.txt
src/sphinxjp.themes.tinkeralizarin.egg-info/dependency_links.txt
src/sphinxjp.themes.tinkeralizarin.egg-info/entry_points.txt
src/sphinxjp.themes.tinkeralizarin.egg-info/namespace_packages.txt
src/sphinxjp.themes.tinkeralizarin.egg-info/not-zip-safe
src/sphinxjp.themes.tinkeralizarin.egg-info/requires.txt
src/sphinxjp.themes.tinkeralizarin.egg-info/top_level.txt
src/sphinxjp/themes/__init__.py
src/sphinxjp/themes/tinkeralizarin/__init__.py
src/sphinxjp/themes/tinkeralizarin/templates/tinkeralizarin/layout.html
src/sphinxjp/themes/tinkeralizarin/templates/tinkeralizarin/theme.conf
src/sphinxjp/themes/tinkeralizarin/templates/tinkeralizarin/static/pygments.css
src/sphinxjp/themes/tinkeralizarin/templates/tinkeralizarin/static/tinkeralizarin.css_t